compasspy/__init__.py
compasspy/client.py
compasspy/errors.py
compasspy/models.py
compasspy-1.2.dist-info/METADATA
compasspy-1.2.dist-info/WHEEL
compasspy-1.2.dist-info/top_level.txt
compasspy-1.2.dist-info/RECORD
