Metadata-Version: 2.1
Name: compasspy
Version: 1.2
Summary: API client for compass.education
Home-page: https://github.com/Artucuno/compasspy
Author: Artucuno
Author-email: artucunov@gmail.com
